maria/__init__.py
maria/_version.py
maria/constants.py
maria/errors.py
maria/array/__init__.py
maria/array/array.py
maria/array/array_list.py
maria/array/detectors.py
maria/array/generation.py
maria/array/alma/aca.cfg
maria/array/alma/alma.cycle1.csv
maria/array/alma/alma.cycle1.f043.csv
maria/array/alma/alma.cycle1.f078.csv
maria/array/alma/alma.cycle1.f100.csv
maria/array/alma/alma.cycle1.f144.csv
maria/array/alma/alma.cycle1.f187.csv
maria/array/alma/alma.cycle1.f243.csv
maria/array/alma/alma.cycle1.f324.csv
maria/array/alma/alma.cycle1.f447.csv
maria/array/alma/alma.cycle1.f661.csv
maria/array/alma/alma.cycle1.f869.csv
maria/array/alma/alma.cycle1.total.csv
maria/array/alma/alma.cycle10.2.cfg
maria/array/alma/alma.cycle10.3.cfg
maria/array/alma/alma.cycle10.4.cfg
maria/array/alma/alma.cycle10.5.cfg
maria/array/alma/alma.cycle10.6.cfg
maria/array/alma/alma.cycle10.7.cfg
maria/array/alma/alma.cycle10.8.cfg
maria/array/alma/alma_f144.csv
maria/array/configs/act.yml
maria/array/configs/alma.yml
maria/array/configs/hd.yml
maria/array/configs/m2.yml
maria/array/configs/so.yml
maria/atmosphere/__init__.py
maria/atmosphere/atmosphere.py
maria/atmosphere/engine.py
maria/atmosphere/extrusion.py
maria/atmosphere/process.py
maria/atmosphere/turbulent_layer.py
maria/band/__init__.py
maria/band/band.py
maria/band/band_list.py
maria/band/format.csv
maria/band/configs/abs.yml
maria/band/configs/act.yml
maria/band/configs/alma.yml
maria/band/configs/atlast.yml
maria/band/configs/m2.yml
maria/band/configs/so.yml
maria/band/configs/test.yml
maria/band/configs/toltec.yml
maria/beam/__init__.py
maria/calibration/__init__.py
maria/calibration/calibration.py
maria/calibration/conversion.py
maria/cmb/__init__.py
maria/cmb/cmb.py
maria/coords/__init__.py
maria/coords/coordinates.py
maria/coords/frame.py
maria/coords/frame.yml
maria/coords/frames.csv
maria/coords/transforms.py
maria/errors/__init__.py
maria/errors/plan.py
maria/functions/__init__.py
maria/functions/radiometry.py
maria-1.4.2.dist-info/METADATA
maria-1.4.2.dist-info/WHEEL
maria-1.4.2.dist-info/licenses/AUTHORS.rst
maria-1.4.2.dist-info/licenses/LICENSE
maria-1.4.2.dist-info/RECORD
