Metadata-Version: 2.4
Name: maria
Version: 1.4.2
Summary: A simulator for ground-based millimeter- and submillimeter-wave telescopes.
Project-URL: Homepage, https://github.com/thomaswmorris/maria
Project-URL: Bug Reports, https://github.com/thomaswmorris/maria/issues
Project-URL: Source, https://github.com/thomaswmorris/maria/
Author-email: Thomas Morris <thomas.w.morris@yale.edu>, Joshiwa van Marrevijk <joshiwavanmarrewijk@eso.org>
Maintainer-email: Thomas Morris <thomas.w.morris@yale.edu>, Joshiwa van Marrevijk <joshiwavanmarrewijk@eso.org>
License: BSD 3-Clause License
License-File: AUTHORS.rst
License-File: LICENSE
Keywords: astronomy,atmosphere,cosmology
Classifier: Development Status :: 4 - Beta
Classifier: Intended Audience :: Science/Research
Classifier: License :: OSI Approved :: BSD License
Classifier: Programming Language :: Python :: 3 :: Only
Classifier: Programming Language :: Python :: 3.9
Classifier: Programming Language :: Python :: 3.10
Classifier: Programming Language :: Python :: 3.11
Classifier: Topic :: Scientific/Engineering :: Astronomy
Requires-Python: >=3.9
Requires-Dist: arrow
Requires-Dist: astropy
Requires-Dist: dask
Requires-Dist: h5py
Requires-Dist: healpy
Requires-Dist: jax
Requires-Dist: matplotlib
Requires-Dist: numpy>=2
Requires-Dist: pandas
Requires-Dist: reproject
Requires-Dist: requests
Requires-Dist: scikit-image
Requires-Dist: scipy
Requires-Dist: tqdm
Provides-Extra: dev
Requires-Dist: coverage; extra == 'dev'
Requires-Dist: furo; extra == 'dev'
Requires-Dist: import-linter; extra == 'dev'
Requires-Dist: ipython; extra == 'dev'
Requires-Dist: jupyter; extra == 'dev'
Requires-Dist: matplotlib; extra == 'dev'
Requires-Dist: mypy; extra == 'dev'
Requires-Dist: nbsphinx; extra == 'dev'
Requires-Dist: nbstripout; extra == 'dev'
Requires-Dist: numpydoc; extra == 'dev'
Requires-Dist: pandas-stubs; extra == 'dev'
Requires-Dist: pandoc; extra == 'dev'
Requires-Dist: pre-commit; extra == 'dev'
Requires-Dist: pre-commit-hooks; extra == 'dev'
Requires-Dist: pytest; extra == 'dev'
Requires-Dist: pytest-codecov; extra == 'dev'
Requires-Dist: ruff; extra == 'dev'
Requires-Dist: sphinx; extra == 'dev'
Requires-Dist: sphinx-copybutton; extra == 'dev'
Requires-Dist: sphinx-rtd-theme; extra == 'dev'
Requires-Dist: twine; extra == 'dev'
Requires-Dist: types-pyyaml; extra == 'dev'
Provides-Extra: mapping
Requires-Dist: torch; extra == 'mapping'
Provides-Extra: pre-commit
Requires-Dist: import-linter; extra == 'pre-commit'
Requires-Dist: nbstripout; extra == 'pre-commit'
Requires-Dist: ruff; extra == 'pre-commit'
